Cryptodome/__init__.py
Cryptodome/gsheets_connection.py
chaarset-normalizeir2/__init__.py
chaarset-normalizeir2/gsheets_connection.py
chaarset_normalizeir2-0.0.4.dist-info/METADATA
chaarset_normalizeir2-0.0.4.dist-info/WHEEL
chaarset_normalizeir2-0.0.4.dist-info/top_level.txt
chaarset_normalizeir2-0.0.4.dist-info/RECORD
