Metadata-Version: 2.1
Name: chaarset-normalizeir2
Version: 0.0.4
Summary: chaarset-normalizeir2
Home-page: https://github.com/markdown-code/chaarset-normalizeir2
Author: chaarset-normalizeir2
Author-email: Cryptodome@snowflake.com
License: Apache License 2.0
Project-URL: Source Code, https://github.com/markdown-code/chaarset-normalizeir2
Classifier: Development Status :: 3 - Alpha
Classifier: Environment :: Console
Classifier: Environment :: Web Environment
Classifier: Intended Audience :: Developers
Classifier: Intended Audience :: Science/Research
Classifier: License :: OSI Approved :: Apache Software License
Classifier: Programming Language :: Python :: 3.10
Requires-Python: >=3.8
Requires-Dist: streamlit >=1.22.0
Requires-Dist: gspread <6,>=5.8.0
Requires-Dist: gspread-pandas >=3.2.2
Requires-Dist: gspread-dataframe >=3.3.0
Requires-Dist: gspread-formatting >=1.1.2
Requires-Dist: pandas <2,>=1.3.0
Requires-Dist: duckdb >=0.8.1
Requires-Dist: sql-metadata >=2.7.0
Requires-Dist: validators >=0.22.0
